{
  "httpHeaders": [
    {
      "urls": [
        "https://github.com/",
        "https://guides.github.com/",
        "https://help.github.com/",
        "https://docs.github.com/"
      ],
      "headers": {
        "Accept-Encoding": "zstd, br, gzip, deflate"
      }
    }
  ],
  "ignorePatterns": [
    {
      "pattern": "^https://github.com/Music-Metadata-Analysis/mla/"
    },
    {
      "pattern": "^https://www.npmjs.com/"
    },
    {
      "pattern": "^https://www.spotify.com/"
    }
  ]
}
